odoo10_addon_storage_image_category_pos-10.0.1.0.1-py3.8-nspkg.pth
odoo/addons/storage_image_category_pos/README.rst
odoo/addons/storage_image_category_pos/__init__.py
odoo/addons/storage_image_category_pos/__manifest__.py
odoo/addons/storage_image_category_pos/i18n/storage_image_category_pos.pot
odoo/addons/storage_image_category_pos/static/description/icon.png
odoo/addons/storage_image_category_pos/views/product_category.xml
odoo10_addon_storage_image_category_pos-10.0.1.0.1.dist-info/METADATA
odoo10_addon_storage_image_category_pos-10.0.1.0.1.dist-info/WHEEL
odoo10_addon_storage_image_category_pos-10.0.1.0.1.dist-info/namespace_packages.txt
odoo10_addon_storage_image_category_pos-10.0.1.0.1.dist-info/top_level.txt
odoo10_addon_storage_image_category_pos-10.0.1.0.1.dist-info/RECORD
